Metadata-Version: 1.0
Name: distributions-oybek
Version: 0.2
Summary: Gaussian_distributions
Home-page: UNKNOWN
Author: UNKNOWN
Author-email: UNKNOWN
License: UNKNOWN
Platform: UNKNOWN
